pySnippetManager-0.1.4.data/scripts/pysnippetmanager
pySnippetManager-0.1.4.dist-info/METADATA
pySnippetManager-0.1.4.dist-info/RECORD
pySnippetManager-0.1.4.dist-info/WHEEL
pySnippetManager-0.1.4.dist-info/top_level.txt
pysnippetmanager/__init__.py
pysnippetmanager/app.py
pysnippetmanager/file_browser.py
pysnippetmanager/snippet.py
pysnippetmanager/text_editor.py
pysnippetmanager/tokens.py
pysnippetmanager/utils.py
