Metadata-Version: 2.1
Name: pySnippetManager
Version: 0.1.4
Summary: A Snippet Manager written in Python
Home-page: http://www.github.com/trombastic/pySnippetManager
Author: Martin Schröder
Author-email: m.schroeder@tu-berlin.de
License: GPL version 3
Platform: OS Independent
Classifier: Development Status :: 4 - Beta
Classifier: Intended Audience :: Developers
Classifier: License :: OSI Approved :: GNU General Public License v3 (GPLv3)
Classifier: Operating System :: POSIX
Classifier: Operating System :: MacOS :: MacOS X
Classifier: Programming Language :: Python
Requires-Dist: pygments
Requires-Dist: pillow
